meteofrance/__init__.py
meteofrance/__main__.py
meteofrance/client.py
krozark_meteofrance-0.3.9.dist-info/LICENSE
krozark_meteofrance-0.3.9.dist-info/METADATA
krozark_meteofrance-0.3.9.dist-info/WHEEL
krozark_meteofrance-0.3.9.dist-info/top_level.txt
krozark_meteofrance-0.3.9.dist-info/RECORD
